django_deepface/__init__.py
django_deepface/admin.py
django_deepface/apps.py
django_deepface/forms.py
django_deepface/models.py
django_deepface/signals.py
django_deepface/urls.py
django_deepface/utils.py
django_deepface/views.py
django_deepface/management/__init__.py
django_deepface/management/commands/__init__.py
django_deepface/management/commands/add_image_tree.py
django_deepface/migrations/0001_initial.py
django_deepface/migrations/0002_initial.py
django_deepface/migrations/__init__.py
django_deepface/templates/base.html
django_deepface/templates/django_deepface/base.html
django_deepface/templates/django_deepface/index.html
django_deepface/templates/django_deepface/login.html
django_deepface/templates/django_deepface/profile.html
django_deepface/tests/__init__.py
django_deepface/tests/conftest.py
django_deepface/tests/settings.py
django_deepface/tests/test_face.webp
django_deepface/tests/test_views.py
django_deepface/tests/urls.py
django_deepface-0.0.7.dist-info/METADATA
django_deepface-0.0.7.dist-info/WHEEL
django_deepface-0.0.7.dist-info/licenses/LICENSE
django_deepface-0.0.7.dist-info/RECORD
