Metadata-Version: 2.4
Name: django-deepface
Version: 0.0.7
Summary: A Django app for face recognition authentication using DeepFace and pgvector
Project-URL: Homepage, https://github.com/topiaruss/django-deepface
Project-URL: Repository, https://github.com/topiaruss/django-deepface
Project-URL: Issues, https://github.com/topiaruss/django-deepface/issues
Author-email: Russ Ferriday <russ.ferriday@gmail.com>
License: MIT
License-File: LICENSE
Keywords: authentication,biometric,deepface,django,face-recognition
Classifier: Development Status :: 3 - Alpha
Classifier: Framework :: Django
Classifier: Framework :: Django :: 4.2
Classifier: Framework :: Django :: 5.0
Classifier: Framework :: Django :: 5.1
Classifier: Intended Audience :: Developers
Classifier: License :: OSI Approved :: MIT License
Classifier: Programming Language :: Python :: 3
Classifier: Programming Language :: Python :: 3.9
Classifier: Programming Language :: Python :: 3.10
Classifier: Programming Language :: Python :: 3.11
Classifier: Topic :: Software Development :: Libraries :: Python Modules
Requires-Python: <3.12,>=3.9
Requires-Dist: deepface>=0.0.79
Requires-Dist: dj-database-url>=2.3.0
Requires-Dist: django<5.2,>=4.2
Requires-Dist: numpy>=1.24.0
Requires-Dist: pgvector>=0.2.4
Requires-Dist: pillow>=10.0.0
Requires-Dist: psycopg[binary]>=3.1.0
Requires-Dist: tf-keras>=2.15.0
Provides-Extra: dev
Requires-Dist: django-stubs>=5.0.0; extra == 'dev'
Requires-Dist: pre-commit>=3.0.0; extra == 'dev'
Requires-Dist: pytest-cov>=4.0; extra == 'dev'
Requires-Dist: pytest-django>=4.5; extra == 'dev'
Requires-Dist: pytest>=7.0; extra == 'dev'
Requires-Dist: ruff>=0.6.0; extra == 'dev'
